snowiecaster/__init__.py
snowiecaster/abstract.py
snowiecaster/backends/__init__.py
snowiecaster/backends/memory/__init__.py
snowiecaster/backends/memory/memory.py
snowiecaster/base.py
snowiecaster-0.1.3.dist-info/METADATA
snowiecaster-0.1.3.dist-info/LICENSE
snowiecaster-0.1.3.dist-info/WHEEL
snowiecaster-0.1.3.dist-info/RECORD
