Metadata-Version: 2.1
Name: snowiecaster
Version: 0.1.3
Summary: 
Author: AndreiErshov
Author-email: mtaprovince04@gmail.com
Requires-Python: >=3.10,<4.0
Classifier: Programming Language :: Python :: 3
Classifier: Programming Language :: Python :: 3.10
Classifier: Programming Language :: Python :: 3.11
